odoo/addons/website_sale_require_login/README.rst
odoo/addons/website_sale_require_login/__init__.py
odoo/addons/website_sale_require_login/__manifest__.py
odoo/addons/website_sale_require_login/controllers/__init__.py
odoo/addons/website_sale_require_login/controllers/main.py
odoo/addons/website_sale_require_login/demo/demo_assets.xml
odoo/addons/website_sale_require_login/i18n/it.po
odoo/addons/website_sale_require_login/i18n/sl.po
odoo/addons/website_sale_require_login/static/description/icon.png
odoo/addons/website_sale_require_login/static/src/js/website_sale_tour_buy_login.tour.js
odoo/addons/website_sale_require_login/tests/__init__.py
odoo/addons/website_sale_require_login/tests/test_checkout.py
odoo/addons/website_sale_require_login/views/website_sale.xml
odoo11_addon_website_sale_require_login-11.0.1.0.0.dist-info/DESCRIPTION.rst
odoo11_addon_website_sale_require_login-11.0.1.0.0.dist-info/METADATA
odoo11_addon_website_sale_require_login-11.0.1.0.0.dist-info/RECORD
odoo11_addon_website_sale_require_login-11.0.1.0.0.dist-info/WHEEL
odoo11_addon_website_sale_require_login-11.0.1.0.0.dist-info/metadata.json
odoo11_addon_website_sale_require_login-11.0.1.0.0.dist-info/top_level.txt
